<results>
<copyright>(c) 2012, Great Britain Historical GIS, University of Portsmouth, UK. Published under the Creative Commons Attribution 2.0 UK: England &amp; Wales License (http://creativecommons.org/licenses/by/2.0/uk/).</copyright>
<place>
<id>12318</id>
<name>GLENTWORTH</name>
<container>LINCOLNSHIRE</container>
<lat>53.3791859494111</lat>
<lon>-0.592482704818971</lon>
<gazetteerText>GLENTWORTH, a parish in Gainsborough district, Lincoln; on the Wolds, 7 miles NE by N of Marton r. station, and 8 ESE of Gainsborough. Post town, Fillingham, under Lincoln. Acres, 3, 043. Real property, &#163;3, 554. Pop., 340. Houses, 58. The property belongs to the Earl of Scarborough. The living is a vicarage in the diocese of Lincoln. Value, &#163;307.* Patron, the Earl of Scarborough. The church is good; and contains a monument of Lord-Chief-Justice Wray, of the time of Elizabeth. There are two alms-houses. (In 1870-72, John Marius Wilson&apos;s Imperial Gazetteer of England and Wales)</gazetteerText>
<links>
<link>http://www.genuki.org.uk/big/eng/LIN/Glentworth/</link>
<link>http://en.wikipedia.org/wiki/Glentworth</link>
<link>http://www.geonames.org/2648419</link>
</links>
<unit>
   <id>10417818</id>
   <status>CP/AP</status>
   <name>GLENTWORTH</name>
</unit>
<unit>
   <id>10417867</id>
   <status>EP</status>
   <name>GLENTWORTH</name>
</unit>
</place>
</results>
