<results>
<copyright>(c) 2012, Great Britain Historical GIS, University of Portsmouth, UK. Published under the Creative Commons Attribution 2.0 UK: England &amp; Wales License (http://creativecommons.org/licenses/by/2.0/uk/).</copyright>
<place>
<id>8983</id>
<name>GRANDBOROUGH</name>
<container>WARWICKSHIRE</container>
<lat>52.2937750276897</lat>
<lon>-1.28640301959523</lon>
<gazetteerText>GRANDBOROUGH, a village and a parish in Rugby district, Warwick. The village stands on the river Leam, near the Oxford canal and the boundary with Northampton, 5 miles SE by E of Birdingbury r. station, and 6 NE of Southam; is a scattered place; and has a post office under Rugby. The parish includes the hamlets of woolscott and Calcutt. Acres, 4, 100. Real property, &#163;7, 510. Pop., 462. Houses, 109. The property is much subdivided. The living is a vicarage in the diocese of Worcester. Value, &#163;185.* Patron, the Rev. R. Kettle. The church is ancient but good; and consists of nave, chancel, and aisles, with a neat spire. There are a national school, and charities &#163;6. (In 1870-72, John Marius Wilson&apos;s Imperial Gazetteer of England and Wales)</gazetteerText>
<links>
<link>http://en.wikipedia.org/wiki/Grandborough</link>
<link>http://www.genuki.org.uk/big/eng/WAR/Grandborough/index.html</link>
<link>http://www.geonames.org/2648223</link>
<link>http://www.british-history.ac.uk/report.asp?compid=57104</link>
</links>
<unit>
   <id>10308800</id>
   <status>AP/CP</status>
   <name>GRANDBOROUGH</name>
</unit>
<unit>
   <id>10308823</id>
   <status>EP</status>
   <name>GRANDBOROUGH</name>
</unit>
</place>
</results>
