<?xml version="1.0" encoding="UTF-8" standalone="no"?>
<geonames style="FULL">
<totalResultsCount>1</totalResultsCount>
<geoname>
<toponymName>Higham Gobion</toponymName>
<name>Higham Gobion</name>
<lat>51.98681</lat>
<lng>-0.39138</lng>
<geonameId>6286580</geonameId>
<countryCode>GB</countryCode>
<countryName>United Kingdom</countryName>
<fcl>S</fcl>
<fcode>CSTL</fcode>
<fclName>spot, building, farm</fclName>
<fcodeName>castle</fcodeName>
<population/>
<alternateNames/>
<elevation/>
<continentCode>EU</continentCode>
<adminCode1 ISO3166-2="ENG">ENG</adminCode1>
<adminName1>England</adminName1>
<adminCode2>Z6</adminCode2>
<adminName2>Central Bedfordshire</adminName2>
<timezone dstOffset="1.0" gmtOffset="0.0">Europe/London</timezone>
<score>19.947162628173828</score>
</geoname>
</geonames>
