<?xml version="1.0" encoding="UTF-8" standalone="no"?>
<geonames style="FULL">
<totalResultsCount>2</totalResultsCount>
<geoname>
<toponymName>Burstock</toponymName>
<name>Burstock</name>
<lat>50.82301</lat>
<lng>-2.8228</lng>
<geonameId>2654223</geonameId>
<countryCode>GB</countryCode>
<countryName>United Kingdom</countryName>
<fcl>P</fcl>
<fcode>PPL</fcode>
<fclName>city, village,...</fclName>
<fcodeName>populated place</fcodeName>
<population/>
<alternateNames>Burstock</alternateNames>
<elevation/>
<continentCode>EU</continentCode>
<adminCode1 ISO3166-2="ENG">ENG</adminCode1>
<adminName1>England</adminName1>
<adminCode2>D6</adminCode2>
<adminName2>Dorset</adminName2>
<adminCode3>19UH</adminCode3>
<adminName3>West Dorset District</adminName3>
<alternateName lang="link">http://en.wikipedia.org/wiki/Burstock</alternateName>
<timezone dstOffset="1.0" gmtOffset="0.0">Europe/London</timezone>
<bbox>
<west>-2.83704</west>
<north>50.832</north>
<east>-2.80856</east>
<south>50.81401</south>
</bbox>
<score>105.5211181640625</score>
</geoname>
<geoname>
<toponymName>Burstock</toponymName>
<name>Burstock</name>
<lat>50.821</lat>
<lng>-2.81925</lng>
<geonameId>7291597</geonameId>
<countryCode>GB</countryCode>
<countryName>United Kingdom</countryName>
<fcl>A</fcl>
<fcode>ADM4</fcode>
<fclName>country, state, region,...</fclName>
<fcodeName>fourth-order administrative division</fcodeName>
<population/>
<alternateNames/>
<elevation/>
<continentCode>EU</continentCode>
<adminCode1 ISO3166-2="ENG">ENG</adminCode1>
<adminName1>England</adminName1>
<adminCode2>D6</adminCode2>
<adminName2>Dorset</adminName2>
<adminCode3>19UH</adminCode3>
<adminName3>West Dorset District</adminName3>
<adminCode4>19UH021</adminCode4>
<adminName4>Burstock</adminName4>
<timezone dstOffset="1.0" gmtOffset="0.0">Europe/London</timezone>
<bbox>
<west>-2.83617</west>
<north>50.83382</north>
<east>-2.80234</east>
<south>50.80818</south>
</bbox>
<score>80.19264221191406</score>
</geoname>
</geonames>
