<?xml version="1.0" encoding="UTF-8" standalone="no"?>
<geonames style="FULL">
<totalResultsCount>1</totalResultsCount>
<geoname>
<toponymName>Clarbeston</toponymName>
<name>Clarbeston</name>
<lat>51.85453</lat>
<lng>-4.83595</lng>
<geonameId>2652944</geonameId>
<countryCode>GB</countryCode>
<countryName>United Kingdom</countryName>
<fcl>P</fcl>
<fcode>PPL</fcode>
<fclName>city, village,...</fclName>
<fcodeName>populated place</fcodeName>
<population/>
<alternateNames>Clarbeston</alternateNames>
<elevation/>
<continentCode>EU</continentCode>
<adminCode1 ISO3166-2="WLS">WLS</adminCode1>
<adminName1>Wales</adminName1>
<adminCode2>Y7</adminCode2>
<adminName2>County of Pembrokeshire</adminName2>
<adminCode3>00NS078</adminCode3>
<adminName3>Wiston</adminName3>
<alternateName lang="link">http://en.wikipedia.org/wiki/Clarbeston</alternateName>
<timezone dstOffset="1.0" gmtOffset="0.0">Europe/London</timezone>
<bbox>
<west>-4.85051</west>
<north>51.86352</north>
<east>-4.82139</east>
<south>51.84554</south>
</bbox>
<score>110.04627990722656</score>
</geoname>
</geonames>
