<?xml version="1.0" encoding="UTF-8" standalone="no"?>
<geonames style="FULL">
<totalResultsCount>2</totalResultsCount>
<geoname>
<toponymName>Llanbister</toponymName>
<name>Llanbister</name>
<lat>52.36342</lat>
<lng>-3.27132</lng>
<geonameId>7297852</geonameId>
<countryCode>GB</countryCode>
<countryName>United Kingdom</countryName>
<fcl>A</fcl>
<fcode>ADM3</fcode>
<fclName>country, state, region,...</fclName>
<fcodeName>third-order administrative division</fcodeName>
<population/>
<alternateNames/>
<elevation/>
<continentCode>EU</continentCode>
<adminCode1 ISO3166-2="WLS">WLS</adminCode1>
<adminName1>Wales</adminName1>
<adminCode2>Y8</adminCode2>
<adminName2>Powys</adminName2>
<adminCode3>00NN042</adminCode3>
<adminName3>Llanbister</adminName3>
<timezone dstOffset="1.0" gmtOffset="0.0">Europe/London</timezone>
<bbox>
<west>-3.34887</west>
<north>52.40483</north>
<east>-3.19377</east>
<south>52.322</south>
</bbox>
<score>114.15132141113281</score>
</geoname>
<geoname>
<toponymName>Llanbister</toponymName>
<name>Llanbister</name>
<lat>52.35134</lat>
<lng>-3.31073</lng>
<geonameId>2644170</geonameId>
<countryCode>GB</countryCode>
<countryName>United Kingdom</countryName>
<fcl>P</fcl>
<fcode>PPL</fcode>
<fclName>city, village,...</fclName>
<fcodeName>populated place</fcodeName>
<population/>
<alternateNames/>
<elevation/>
<continentCode>EU</continentCode>
<adminCode1 ISO3166-2="WLS">WLS</adminCode1>
<adminName1>Wales</adminName1>
<adminCode2>Y8</adminCode2>
<adminName2>Powys</adminName2>
<adminCode3>00NN042</adminCode3>
<adminName3>Llanbister</adminName3>
<timezone dstOffset="1.0" gmtOffset="0.0">Europe/London</timezone>
<bbox>
<west>-3.32546</west>
<north>52.36034</north>
<east>-3.29601</east>
<south>52.34235</south>
</bbox>
<score>65.45857238769531</score>
</geoname>
</geonames>
