<?xml version="1.0" encoding="UTF-8" standalone="no"?>
<geonames style="FULL">
<totalResultsCount>1</totalResultsCount>
<geoname>
<toponymName>Audley</toponymName>
<name>Audley</name>
<lat>53.05</lat>
<lng>-2.3</lng>
<geonameId>2656792</geonameId>
<countryCode>GB</countryCode>
<countryName>United Kingdom</countryName>
<fcl>P</fcl>
<fcode>PPL</fcode>
<fclName>city, village,...</fclName>
<fcodeName>populated place</fcodeName>
<population>5638</population>
<alternateNames>Audley</alternateNames>
<elevation/>
<continentCode>EU</continentCode>
<adminCode1 ISO3166-2="ENG">ENG</adminCode1>
<adminName1>England</adminName1>
<adminCode2>M9</adminCode2>
<adminName2>Staffordshire</adminName2>
<adminCode3>41UE</adminCode3>
<adminName3>Newcastle-under-Lyme District</adminName3>
<alternateName lang="link">http://en.wikipedia.org/wiki/Audley%2C_Staffordshire</alternateName>
<timezone dstOffset="1.0" gmtOffset="0.0">Europe/London</timezone>
<bbox>
<west>-2.31496</west>
<north>53.05899</north>
<east>-2.28504</east>
<south>53.04101</south>
</bbox>
<score>108.89397430419922</score>
</geoname>
</geonames>
