<results>
<copyright>(c) 2012, Great Britain Historical GIS, University of Portsmouth, UK. Published under the Creative Commons Attribution 2.0 UK: England &amp; Wales License (http://creativecommons.org/licenses/by/2.0/uk/).</copyright>
<place>
<id>3221</id>
<name>LLANFIHANGEL ABERGWESYN</name>
<container>BRECKNOCKSHIRE</container>
<lat>52.1855579023829</lat>
<lon>-3.65694238421905</lon>
<gazetteerText>LLANFIHANGEL-ABERGWESSIN, a parish, with a small village, in Builth district, Brecon; on the river Irvon, at the influx of the Gwessin, under Drugarn mountain, 12 miles W by N of Builth. Post town, Builth, Breconshire. Acres, 6,836. Real property, &#163;652. Pop., 355. Houses, 56. The property is divided among a few. Lwyn Madoc is a chief residence. Most of the land is moorish and mountainous. Drugarn mountain has an altitude of 2,071 feet. Slate and lead ore are found. The living is a p. curacy, united with the p. curacy of Llanddewi-Abergwessin, in the diocese of St. David&apos;s. Value and patron, not reported. The church is tolerable. Charities, &#163;13. (In 1870-72, John Marius Wilson&apos;s Imperial Gazetteer of England and Wales)</gazetteerText>
<links>
<link>http://www.genuki.org.uk/big/wal/BRE/LlanfihangelAbergwesyn/index.html</link>
</links>
<unit>
   <id>10094550</id>
   <status>AP/CP</status>
   <name>LLANFIHANGEL ABERGWESYN</name>
</unit>
</place>
</results>
