<results>
<copyright>(c) 2012, Great Britain Historical GIS, University of Portsmouth, UK. Published under the Creative Commons Attribution 2.0 UK: England &amp; Wales License (http://creativecommons.org/licenses/by/2.0/uk/).</copyright>
<place>
<id>2228</id>
<name>ST WENN</name>
<container>CORNWALL</container>
<lat>50.4555072665773</lat>
<lon>-4.86894212784238</lon>
<gazetteerText>WENN (St.), a parish in St. Columb district, Cornwall; 4 miles ENE of St. Columb-Major, and 12 W of Bodmin-Road r. station. It was known at Domesday as San Wena; and it has two annual fairs. Post town, Bodmin. Acres, 4,546. Real property, &#163;3,352. Pop. in 1851, 650; in 1861, 580. Houses, 120. Tregotha, now a farmhouse, was the birthplace of Archbishop Tregury of the 15th century. The living is a vicarage in the diocese of Exeter. Value, &#163;161.* Patron, W. Rashleigh, Esq. The church was rebuilt in 1825, and. restored in 1868. There are a Wesleyan chapel and national schools. (In 1870-72, John Marius Wilson&apos;s Imperial Gazetteer of England and Wales)</gazetteerText>
<links>
<link>http://www.genuki.org.uk/big/eng/Cornwall/StWenn/index.html</link>
<link>http://en.wikipedia.org/wiki/St_Wenn</link>
</links>
<unit>
   <id>10049209</id>
   <status>AP/CP</status>
   <name>ST WENN</name>
</unit>
<unit>
   <id>10086243</id>
   <status>EP</status>
   <name>ST WENN</name>
</unit>
</place>
</results>
