<results>
<copyright>(c) 2012, Great Britain Historical GIS, University of Portsmouth, UK. Published under the Creative Commons Attribution 2.0 UK: England &amp; Wales License (http://creativecommons.org/licenses/by/2.0/uk/).</copyright>
<place>
<id>6403</id>
<name>SOUTHFLEET</name>
<container>KENT</container>
<lat>51.4124609890452</lat>
<lon>0.314662179246732</lon>
<gazetteerText>SOUTHFLEET, a village and a parish in Dartford district, Kent. The village stands near Watling-street, 3 miles SW of Gravesend r. station; originated in the Roman station Vagniac&#230;, on Watling-street; was known at Domesday as Suthfleta; took that name and its present one from a flete or creek, which came to it from the Thames at Northfleet, but is now shut out by an embankment; is much frequented by visitors; and has a post-office under Gravesend. The parish contains also the hamlets of Betsam and Westwood, and the gardens of Spring-Head, famous for water-cresses. Acres, 2,340. Real property, &#163;4,856. Pop., 717. Houses, 155. The property is divided among a few. Many Roman relics, including a milestone, a sarcophagus, earthen vessels, glass urns, trinkets, and coins, have been found. The living is a rectory in the diocese of Rochester. Value, &#163;789.* Patron, the Bishop of R. The church is decorated English. There is an endowed school with &#163;20 a year. (In 1870-72, John Marius Wilson&apos;s Imperial Gazetteer of England and Wales)</gazetteerText>
<links>
<link>http://en.wikipedia.org/wiki/Southfleet</link>
<link>http://www.nwkfhs.org.uk/STHF_plc.htm</link>
<link>http://www.geonames.org/2637421</link>
</links>
<unit>
   <id>10226636</id>
   <status>CP/AP</status>
   <name>SOUTHFLEET</name>
</unit>
<unit>
   <id>10226650</id>
   <status>EP</status>
   <name>SOUTHFLEET</name>
</unit>
</place>
</results>
