<results>
<copyright>(c) 2012, Great Britain Historical GIS, University of Portsmouth, UK. Published under the Creative Commons Attribution 2.0 UK: England &amp; Wales License (http://creativecommons.org/licenses/by/2.0/uk/).</copyright>
<place>
<id>11955</id>
<name>COLEBY</name>
<container>LINCOLNSHIRE</container>
<lat>53.1349319568523</lat>
<lon>-0.54185321683926</lon>
<gazetteerText>COLEBY, a parish in the district and county of Lincoln; on the Wolds, near Ermine-street, 5 miles E of Swinderby r. station and 8 S of Lincoln. Post town, Harmston, under Lincoln. Acres, 2, 600. Real property, &#163;4, 274. Pop., 458. Houses, 104. The property is divided among a few. Coleby Hall, the seat of the Temple family, is a Tudor edifice by Sir W. Chambers. Limestone occurs; and many Roman remains have been found. The living is a vicarage in the diocese of Lincoln. Value, &#163;126.* Patron, Oriel College, Oxford. The church is partly Norman, partly of later dates; and has a fine spire and a font. There are a Wesleyan chapel, and charities &#163;6. (In 1870-72, John Marius Wilson&apos;s Imperial Gazetteer of England and Wales)</gazetteerText>
<links>
<link>http://en.wikipedia.org/wiki/Coleby</link>
<link>http://www.genuki.org.uk/big/eng/LIN/Coleby/</link>
<link>http://www.geonames.org/2652592</link>
</links>
<unit>
   <id>10408362</id>
   <status>AP/CP</status>
   <name>COLEBY</name>
</unit>
<unit>
   <id>10408374</id>
   <status>EP</status>
   <name>COLEBY</name>
</unit>
</place>
</results>
