<results>
<copyright>(c) 2012, Great Britain Historical GIS, University of Portsmouth, UK. Published under the Creative Commons Attribution 2.0 UK: England &amp; Wales License (http://creativecommons.org/licenses/by/2.0/uk/).</copyright>
<place>
<id>3971</id>
<name>METTON</name>
<container>NORFOLK</container>
<lat>52.8869972752217</lat>
<lon>1.266388029816</lon>
<gazetteerText>METTON, a parish in Erpingham district, Norfolk; 3&#188; miles S by W of Cromer, and 17 NE of Elmham r. Station. Post town, Ronghton, under Norwich. Acres, 660. Real property, &#163;897. Pop., 78. Houses, 19. The property is divided among a few. The manor belongs to John Ketton, Esq. The living is a rectory, annexed to the rectory of Felbrigg, in the diocese of Norwich. The church was recently in disrepair. (In 1870-72, John Marius Wilson&apos;s Imperial Gazetteer of England and Wales)</gazetteerText>
<links>
<link>http://www.origins.org.uk/genuki/NFK/places/m/metton/</link>
<link>http://en.wikipedia.org/wiki/Metton</link>
</links>
<unit>
   <id>10123914</id>
   <status>AP/CP</status>
   <name>METTON</name>
</unit>
</place>
</results>
