<results>
<copyright>(c) 2012, Great Britain Historical GIS, University of Portsmouth, UK. Published under the Creative Commons Attribution 2.0 UK: England &amp; Wales License (http://creativecommons.org/licenses/by/2.0/uk/).</copyright>
<place>
<id>13337</id>
<name>THORN FALCON</name>
<container>SOMERSET</container>
<lat>51.0045060427676</lat>
<lon>-3.02133054652905</lon>
<gazetteerText>THORNE-FALCON, a parish in Taunton district, Somerset; 3&#190; miles E of Taunton r. station. Post town, Taunton. Acres, 814. Real property, &#163;1,635. Pop, 196. Houses, 42. The living is a rectory in the diocese of Bath and Wells. Value, &#163;296.* Patron, J. Batten, Esq. The church is ancient but good. (In 1870-72, John Marius Wilson&apos;s Imperial Gazetteer of England and Wales)</gazetteerText>
<links>
<link>http://en.wikipedia.org/wiki/Thornfalcon</link>
<link>http://www.genuki.org.uk/big/eng/SOM/ThorneFalcon/index.html</link>
<link>http://www.geonames.org/2635990</link>
</links>
<unit>
   <id>10444512</id>
   <status>AP/CP</status>
   <name>THORN FALCON</name>
</unit>
<unit>
   <id>10444561</id>
   <status>EP</status>
   <name>THORN FALCON</name>
</unit>
</place>
</results>
